Hubstaff/Hubstaff.py
Hubstaff/__init__.py
Hubstaff-1.1.dist-info/LICENSE
Hubstaff-1.1.dist-info/METADATA
Hubstaff-1.1.dist-info/WHEEL
Hubstaff-1.1.dist-info/top_level.txt
Hubstaff-1.1.dist-info/RECORD
