Metadata-Version: 2.1
Name: Hubstaff
Version: 1.1
Summary: A python library working with Hubstaff
Author-email: Ankushtpss <ankushkumartpss@gmail.com>
Project-URL: Homepage, https://github.com/Ankushtpss/Hubstaff
Project-URL: Bug Tracker, https://github.com/Ankushtpss/Hubstaff/issues
Keywords: Hubstaff,Hub staff,Hubstaff SDK,Hubstaff library
Classifier: Programming Language :: Python :: 3
Classifier: License :: OSI Approved :: MIT License
Classifier: Operating System :: OS Independent
Requires-Python: >=3.8
License-File: LICENSE
Requires-Dist: requests
Requires-Dist: sys
